{
  "field_id": "zone_1",
  "sensors": [
    {
      "sensor_id": "s_01",
      "status": "active",
      "battery_level": 50,
      "readings": [
        {
          "timestamp": "2026-02-20T15:00:00Z",
          "soil_moisture": 27.8,
          "ec": 1.07,
          "soil_temperature": 15.28,
          "ph": 6.35
        },
        {
          "timestamp": "2026-02-20T16:00:00Z",
          "soil_moisture": 26.74,
          "ec": 1.13,
          "soil_temperature": 15.88,
          "ph": 6.32
        },
        {
          "timestamp": "2026-02-20T17:00:00Z",
          "soil_moisture": 26.88,
          "ec": 1.11,
          "soil_temperature": 16.28,
          "ph": 6.26
        },
        {
          "timestamp": "2026-02-20T18:00:00Z",
          "soil_moisture": 28.24,
          "ec": 1.13,
          "soil_temperature": 17.09,
          "ph": 6.32
        },
        {
          "timestamp": "2026-02-20T19:00:00Z",
          "soil_moisture": 27.81,
          "ec": 1.14,
          "soil_temperature": 17.55,
          "ph": 6.32
        },
        {
          "timestamp": "2026-02-20T20:00:00Z",
          "soil_moisture": 28.37,
          "ec": 1.1,
          "soil_temperature": 17.67,
          "ph": 6.31
        },
        {
          "timestamp": "2026-02-20T21:00:00Z",
          "soil_moisture": 27.05,
          "ec": 1.11,
          "soil_temperature": 17.65,
          "ph": 6.25
        },
        {
          "timestamp": "2026-02-20T22:00:00Z",
          "soil_moisture": 28.92,
          "ec": 1.11,
          "soil_temperature": 18.43,
          "ph": 6.32
        },
        {
          "timestamp": "2026-02-20T23:00:00Z",
          "soil_moisture": 27.34,
          "ec": 1.15,
          "soil_temperature": 19.28,
          "ph": 6.31
        },
        {
          "timestamp": "2026-02-21T00:00:00Z",
          "soil_moisture": 28.56,
          "ec": 1.15,
          "soil_temperature": 19.16,
          "ph": 6.34
        },
        {
          "timestamp": "2026-02-21T01:00:00Z",
          "soil_moisture": 29.15,
          "ec": 1.14,
          "soil_temperature": 19.63,
          "ph": 6.29
        },
        {
          "timestamp": "2026-02-21T02:00:00Z",
          "soil_moisture": 29.17,
          "ec": 1.16,
          "soil_temperature": 19.61,
          "ph": 6.31
        },
        {
          "timestamp": "2026-02-21T03:00:00Z",
          "soil_moisture": 28.23,
          "ec": 1.14,
          "soil_temperature": 20.72,
          "ph": 6.31
        },
        {
          "timestamp": "2026-02-21T04:00:00Z",
          "soil_moisture": 27.92,
          "ec": 1.17,
          "soil_temperature": 21.37,
          "ph": 6.34
        },
        {
          "timestamp": "2026-02-21T05:00:00Z",
          "soil_moisture": 28.77,
          "ec": 1.16,
          "soil_temperature": 21.04,
          "ph": 6.35
        },
        {
          "timestamp": "2026-02-21T06:00:00Z",
          "soil_moisture": 29.33,
          "ec": 1.15,
          "soil_temperature": 21.75,
          "ph": 6.35
        },
        {
          "timestamp": "2026-02-21T07:00:00Z",
          "soil_moisture": 28.94,
          "ec": 1.12,
          "soil_temperature": 22.26,
          "ph": 6.27
        },
        {
          "timestamp": "2026-02-21T08:00:00Z",
          "soil_moisture": 28.57,
          "ec": 1.12,
          "soil_temperature": 22.18,
          "ph": 6.27
        },
        {
          "timestamp": "2026-02-21T09:00:00Z",
          "soil_moisture": 30.07,
          "ec": 1.18,
          "soil_temperature": 22.75,
          "ph": 6.29
        },
        {
          "timestamp": "2026-02-21T10:00:00Z",
          "soil_moisture": 28.65,
          "ec": 1.16,
          "soil_temperature": 23.61,
          "ph": 6.28
        },
        {
          "timestamp": "2026-02-21T11:00:00Z",
          "soil_moisture": 28.69,
          "ec": 1.18,
          "soil_temperature": 23.63,
          "ph": 6.29
        },
        {
          "timestamp": "2026-02-21T12:00:00Z",
          "soil_moisture": 29.07,
          "ec": 1.16,
          "soil_temperature": 24.25,
          "ph": 6.26
        },
        {
          "timestamp": "2026-02-21T13:00:00Z",
          "soil_moisture": 30.54,
          "ec": 1.13,
          "soil_temperature": 24.24,
          "ph": 6.31
        },
        {
          "timestamp": "2026-02-21T14:00:00Z",
          "soil_moisture": 29.15,
          "ec": 1.17,
          "soil_temperature": 24.54,
          "ph": 6.26
        }
      ]
    },
    {
      "sensor_id": "s_02",
      "status": "active",
      "battery_level": 73,
      "readings": [
        {
          "timestamp": "2026-02-20T15:00:00Z",
          "soil_moisture": 27.09,
          "ec": 1.1,
          "soil_temperature": 15.42,
          "ph": 6.29
        },
        {
          "timestamp": "2026-02-20T16:00:00Z",
          "soil_moisture": 27.8,
          "ec": 1.11,
          "soil_temperature": 16.28,
          "ph": 6.35
        },
        {
          "timestamp": "2026-02-20T17:00:00Z",
          "soil_moisture": 26.54,
          "ec": 1.12,
          "soil_temperature": 16.77,
          "ph": 6.31
        },
        {
          "timestamp": "2026-02-20T18:00:00Z",
          "soil_moisture": 27.13,
          "ec": 1.08,
          "soil_temperature": 16.98,
          "ph": 6.31
        },
        {
          "timestamp": "2026-02-20T19:00:00Z",
          "soil_moisture": 28.02,
          "ec": 1.08,
          "soil_temperature": 16.83,
          "ph": 6.34
        },
        {
          "timestamp": "2026-02-20T20:00:00Z",
          "soil_moisture": 27.66,
          "ec": 1.12,
          "soil_temperature": 18.1,
          "ph": 6.34
        },
        {
          "timestamp": "2026-02-20T21:00:00Z",
          "soil_moisture": 27.73,
          "ec": 1.12,
          "soil_temperature": 17.94,
          "ph": 6.26
        },
        {
          "timestamp": "2026-02-20T22:00:00Z",
          "soil_moisture": 28.34,
          "ec": 1.15,
          "soil_temperature": 18.08,
          "ph": 6.26
        },
        {
          "timestamp": "2026-02-20T23:00:00Z",
          "soil_moisture": 28.38,
          "ec": 1.15,
          "soil_temperature": 18.77,
          "ph": 6.32
        },
        {
          "timestamp": "2026-02-21T00:00:00Z",
          "soil_moisture": 27.66,
          "ec": 1.14,
          "soil_temperature": 19.3,
          "ph": 6.32
        },
        {
          "timestamp": "2026-02-21T01:00:00Z",
          "soil_moisture": 28.04,
          "ec": 1.13,
          "soil_temperature": 19.68,
          "ph": 6.35
        },
        {
          "timestamp": "2026-02-21T02:00:00Z",
          "soil_moisture": 27.96,
          "ec": 1.13,
          "soil_temperature": 20.29,
          "ph": 6.35
        },
        {
          "timestamp": "2026-02-21T03:00:00Z",
          "soil_moisture": 29.74,
          "ec": 1.16,
          "soil_temperature": 20.22,
          "ph": 6.26
        },
        {
          "timestamp": "2026-02-21T04:00:00Z",
          "soil_moisture": 28.82,
          "ec": 1.15,
          "soil_temperature": 20.8,
          "ph": 6.33
        },
        {
          "timestamp": "2026-02-21T05:00:00Z",
          "soil_moisture": 28.34,
          "ec": 1.17,
          "soil_temperature": 21.19,
          "ph": 6.28
        },
        {
          "timestamp": "2026-02-21T06:00:00Z",
          "soil_moisture": 28.28,
          "ec": 1.15,
          "soil_temperature": 21.52,
          "ph": 6.3
        },
        {
          "timestamp": "2026-02-21T07:00:00Z",
          "soil_moisture": 30.09,
          "ec": 1.17,
          "soil_temperature": 21.65,
          "ph": 6.35
        },
        {
          "timestamp": "2026-02-21T08:00:00Z",
          "soil_moisture": 29.83,
          "ec": 1.15,
          "soil_temperature": 22.62,
          "ph": 6.28
        },
        {
          "timestamp": "2026-02-21T09:00:00Z",
          "soil_moisture": 29.93,
          "ec": 1.15,
          "soil_temperature": 22.91,
          "ph": 6.31
        },
        {
          "timestamp": "2026-02-21T10:00:00Z",
          "soil_moisture": 29.58,
          "ec": 1.12,
          "soil_temperature": 22.95,
          "ph": 6.27
        },
        {
          "timestamp": "2026-02-21T11:00:00Z",
          "soil_moisture": 29.35,
          "ec": 1.13,
          "soil_temperature": 24.08,
          "ph": 6.32
        },
        {
          "timestamp": "2026-02-21T12:00:00Z",
          "soil_moisture": 29.86,
          "ec": 1.17,
          "soil_temperature": 24.26,
          "ph": 6.25
        },
        {
          "timestamp": "2026-02-21T13:00:00Z",
          "soil_moisture": 28.97,
          "ec": 1.19,
          "soil_temperature": 24.29,
          "ph": 6.35
        },
        {
          "timestamp": "2026-02-21T14:00:00Z",
          "soil_moisture": 29.73,
          "ec": 1.18,
          "soil_temperature": 24.87,
          "ph": 6.34
        }
      ]
    },
    {
      "sensor_id": "s_03",
      "status": "active",
      "battery_level": 61,
      "readings": [
        {
          "timestamp": "2026-02-20T15:00:00Z",
          "soil_moisture": 26.1,
          "ec": 1.11,
          "soil_temperature": 15.81,
          "ph": 6.28
        },
        {
          "timestamp": "2026-02-20T16:00:00Z",
          "soil_moisture": 26.27,
          "ec": 1.08,
          "soil_temperature": 15.7,
          "ph": 6.33
        },
        {
          "timestamp": "2026-02-20T17:00:00Z",
          "soil_moisture": 26.43,
          "ec": 1.11,
          "soil_temperature": 16.77,
          "ph": 6.34
        },
        {
          "timestamp": "2026-02-20T18:00:00Z",
          "soil_moisture": 27.67,
          "ec": 1.08,
          "soil_temperature": 17.36,
          "ph": 6.29
        },
        {
          "timestamp": "2026-02-20T19:00:00Z",
          "soil_moisture": 28.38,
          "ec": 1.12,
          "soil_temperature": 17.66,
          "ph": 6.28
        },
        {
          "timestamp": "2026-02-20T20:00:00Z",
          "soil_moisture": 28.67,
          "ec": 1.14,
          "soil_temperature": 17.74,
          "ph": 6.33
        },
        {
          "timestamp": "2026-02-20T21:00:00Z",
          "soil_moisture": 28.13,
          "ec": 1.1,
          "soil_temperature": 17.63,
          "ph": 6.35
        },
        {
          "timestamp": "2026-02-20T22:00:00Z",
          "soil_moisture": 29.01,
          "ec": 1.15,
          "soil_temperature": 18.71,
          "ph": 6.25
        },
        {
          "timestamp": "2026-02-20T23:00:00Z",
          "soil_moisture": 29.16,
          "ec": 1.15,
          "soil_temperature": 19.1,
          "ph": 6.34
        },
        {
          "timestamp": "2026-02-21T00:00:00Z",
          "soil_moisture": 28.96,
          "ec": 1.12,
          "soil_temperature": 19.0,
          "ph": 6.29
        },
        {
          "timestamp": "2026-02-21T01:00:00Z",
          "soil_moisture": 29.21,
          "ec": 1.11,
          "soil_temperature": 19.9,
          "ph": 6.33
        },
        {
          "timestamp": "2026-02-21T02:00:00Z",
          "soil_moisture": 29.08,
          "ec": 1.16,
          "soil_temperature": 20.43,
          "ph": 6.32
        },
        {
          "timestamp": "2026-02-21T03:00:00Z",
          "soil_moisture": 27.87,
          "ec": 1.12,
          "soil_temperature": 20.8,
          "ph": 6.3
        },
        {
          "timestamp": "2026-02-21T04:00:00Z",
          "soil_moisture": 29.3,
          "ec": 1.16,
          "soil_temperature": 21.25,
          "ph": 6.32
        },
        {
          "timestamp": "2026-02-21T05:00:00Z",
          "soil_moisture": 29.03,
          "ec": 1.15,
          "soil_temperature": 20.88,
          "ph": 6.32
        },
        {
          "timestamp": "2026-02-21T06:00:00Z",
          "soil_moisture": 29.6,
          "ec": 1.17,
          "soil_temperature": 21.44,
          "ph": 6.27
        },
        {
          "timestamp": "2026-02-21T07:00:00Z",
          "soil_moisture": 28.9,
          "ec": 1.13,
          "soil_temperature": 21.66,
          "ph": 6.25
        },
        {
          "timestamp": "2026-02-21T08:00:00Z",
          "soil_moisture": 28.6,
          "ec": 1.15,
          "soil_temperature": 22.39,
          "ph": 6.3
        },
        {
          "timestamp": "2026-02-21T09:00:00Z",
          "soil_moisture": 29.54,
          "ec": 1.14,
          "soil_temperature": 22.61,
          "ph": 6.29
        },
        {
          "timestamp": "2026-02-21T10:00:00Z",
          "soil_moisture": 29.08,
          "ec": 1.17,
          "soil_temperature": 23.09,
          "ph": 6.32
        },
        {
          "timestamp": "2026-02-21T11:00:00Z",
          "soil_moisture": 30.21,
          "ec": 1.15,
          "soil_temperature": 23.56,
          "ph": 6.31
        },
        {
          "timestamp": "2026-02-21T12:00:00Z",
          "soil_moisture": 28.88,
          "ec": 1.14,
          "soil_temperature": 23.66,
          "ph": 6.32
        },
        {
          "timestamp": "2026-02-21T13:00:00Z",
          "soil_moisture": 29.52,
          "ec": 1.18,
          "soil_temperature": 24.12,
          "ph": 6.33
        },
        {
          "timestamp": "2026-02-21T14:00:00Z",
          "soil_moisture": 30.49,
          "ec": 1.14,
          "soil_temperature": 24.65,
          "ph": 6.31
        }
      ]
    },
    {
      "sensor_id": "s_04",
      "status": "active",
      "battery_level": 55,
      "readings": [
        {
          "timestamp": "2026-02-20T15:00:00Z",
          "soil_moisture": 27.56,
          "ec": 1.08,
          "soil_temperature": 15.47,
          "ph": 6.3
        },
        {
          "timestamp": "2026-02-20T16:00:00Z",
          "soil_moisture": 27.03,
          "ec": 1.08,
          "soil_temperature": 15.82,
          "ph": 6.32
        },
        {
          "timestamp": "2026-02-20T17:00:00Z",
          "soil_moisture": 27.31,
          "ec": 1.1,
          "soil_temperature": 16.07,
          "ph": 6.34
        },
        {
          "timestamp": "2026-02-20T18:00:00Z",
          "soil_moisture": 27.39,
          "ec": 1.09,
          "soil_temperature": 17.14,
          "ph": 6.34
        },
        {
          "timestamp": "2026-02-20T19:00:00Z",
          "soil_moisture": 28.18,
          "ec": 1.11,
          "soil_temperature": 17.33,
          "ph": 6.33
        },
        {
          "timestamp": "2026-02-20T20:00:00Z",
          "soil_moisture": 27.6,
          "ec": 1.13,
          "soil_temperature": 17.6,
          "ph": 6.33
        },
        {
          "timestamp": "2026-02-20T21:00:00Z",
          "soil_moisture": 28.2,
          "ec": 1.1,
          "soil_temperature": 18.05,
          "ph": 6.35
        },
        {
          "timestamp": "2026-02-20T22:00:00Z",
          "soil_moisture": 28.58,
          "ec": 1.14,
          "soil_temperature": 18.58,
          "ph": 6.31
        },
        {
          "timestamp": "2026-02-20T23:00:00Z",
          "soil_moisture": 27.31,
          "ec": 1.1,
          "soil_temperature": 19.06,
          "ph": 6.27
        },
        {
          "timestamp": "2026-02-21T00:00:00Z",
          "soil_moisture": 27.7,
          "ec": 1.13,
          "soil_temperature": 19.3,
          "ph": 6.35
        },
        {
          "timestamp": "2026-02-21T01:00:00Z",
          "soil_moisture": 28.57,
          "ec": 1.14,
          "soil_temperature": 19.94,
          "ph": 6.34
        },
        {
          "timestamp": "2026-02-21T02:00:00Z",
          "soil_moisture": 29.02,
          "ec": 1.16,
          "soil_temperature": 20.06,
          "ph": 6.28
        },
        {
          "timestamp": "2026-02-21T03:00:00Z",
          "soil_moisture": 27.9,
          "ec": 1.12,
          "soil_temperature": 20.92,
          "ph": 6.28
        },
        {
          "timestamp": "2026-02-21T04:00:00Z",
          "soil_moisture": 28.1,
          "ec": 1.11,
          "soil_temperature": 21.32,
          "ph": 6.33
        },
        {
          "timestamp": "2026-02-21T05:00:00Z",
          "soil_moisture": 29.35,
          "ec": 1.12,
          "soil_temperature": 21.76,
          "ph": 6.34
        },
        {
          "timestamp": "2026-02-21T06:00:00Z",
          "soil_moisture": 29.86,
          "ec": 1.15,
          "soil_temperature": 21.72,
          "ph": 6.28
        },
        {
          "timestamp": "2026-02-21T07:00:00Z",
          "soil_moisture": 30.2,
          "ec": 1.15,
          "soil_temperature": 21.99,
          "ph": 6.31
        },
        {
          "timestamp": "2026-02-21T08:00:00Z",
          "soil_moisture": 29.69,
          "ec": 1.13,
          "soil_temperature": 22.66,
          "ph": 6.3
        },
        {
          "timestamp": "2026-02-21T09:00:00Z",
          "soil_moisture": 29.03,
          "ec": 1.16,
          "soil_temperature": 22.73,
          "ph": 6.3
        },
        {
          "timestamp": "2026-02-21T10:00:00Z",
          "soil_moisture": 30.19,
          "ec": 1.16,
          "soil_temperature": 23.45,
          "ph": 6.29
        },
        {
          "timestamp": "2026-02-21T11:00:00Z",
          "soil_moisture": 29.18,
          "ec": 1.13,
          "soil_temperature": 23.74,
          "ph": 6.3
        },
        {
          "timestamp": "2026-02-21T12:00:00Z",
          "soil_moisture": 30.1,
          "ec": 1.14,
          "soil_temperature": 23.92,
          "ph": 6.25
        },
        {
          "timestamp": "2026-02-21T13:00:00Z",
          "soil_moisture": 30.38,
          "ec": 1.13,
          "soil_temperature": 24.93,
          "ph": 6.28
        },
        {
          "timestamp": "2026-02-21T14:00:00Z",
          "soil_moisture": 30.84,
          "ec": 1.15,
          "soil_temperature": 24.95,
          "ph": 6.26
        }
      ]
    },
    {
      "sensor_id": "s_05",
      "status": "active",
      "battery_level": 60,
      "readings": [
        {
          "timestamp": "2026-02-20T15:00:00Z",
          "soil_moisture": 26.29,
          "ec": 1.08,
          "soil_temperature": 15.22,
          "ph": 6.31
        },
        {
          "timestamp": "2026-02-20T16:00:00Z",
          "soil_moisture": 26.38,
          "ec": 1.08,
          "soil_temperature": 15.76,
          "ph": 6.29
        },
        {
          "timestamp": "2026-02-20T17:00:00Z",
          "soil_moisture": 26.31,
          "ec": 1.11,
          "soil_temperature": 16.59,
          "ph": 6.31
        },
        {
          "timestamp": "2026-02-20T18:00:00Z",
          "soil_moisture": 27.83,
          "ec": 1.09,
          "soil_temperature": 16.75,
          "ph": 6.35
        },
        {
          "timestamp": "2026-02-20T19:00:00Z",
          "soil_moisture": 28.42,
          "ec": 1.09,
          "soil_temperature": 16.99,
          "ph": 6.27
        },
        {
          "timestamp": "2026-02-20T20:00:00Z",
          "soil_moisture": 27.91,
          "ec": 1.13,
          "soil_temperature": 18.07,
          "ph": 6.32
        },
        {
          "timestamp": "2026-02-20T21:00:00Z",
          "soil_moisture": 28.69,
          "ec": 1.1,
          "soil_temperature": 17.74,
          "ph": 6.26
        },
        {
          "timestamp": "2026-02-20T22:00:00Z",
          "soil_moisture": 28.63,
          "ec": 1.12,
          "soil_temperature": 18.16,
          "ph": 6.27
        },
        {
          "timestamp": "2026-02-20T23:00:00Z",
          "soil_moisture": 27.99,
          "ec": 1.13,
          "soil_temperature": 18.99,
          "ph": 6.27
        },
        {
          "timestamp": "2026-02-21T00:00:00Z",
          "soil_moisture": 27.83,
          "ec": 1.12,
          "soil_temperature": 19.31,
          "ph": 6.34
        },
        {
          "timestamp": "2026-02-21T01:00:00Z",
          "soil_moisture": 29.47,
          "ec": 1.16,
          "soil_temperature": 19.56,
          "ph": 6.32
        },
        {
          "timestamp": "2026-02-21T02:00:00Z",
          "soil_moisture": 29.4,
          "ec": 1.16,
          "soil_temperature": 19.99,
          "ph": 6.33
        },
        {
          "timestamp": "2026-02-21T03:00:00Z",
          "soil_moisture": 28.39,
          "ec": 1.11,
          "soil_temperature": 20.04,
          "ph": 6.32
        },
        {
          "timestamp": "2026-02-21T04:00:00Z",
          "soil_moisture": 28.11,
          "ec": 1.13,
          "soil_temperature": 20.68,
          "ph": 6.34
        },
        {
          "timestamp": "2026-02-21T05:00:00Z",
          "soil_moisture": 29.92,
          "ec": 1.16,
          "soil_temperature": 20.89,
          "ph": 6.29
        },
        {
          "timestamp": "2026-02-21T06:00:00Z",
          "soil_moisture": 29.57,
          "ec": 1.16,
          "soil_temperature": 21.25,
          "ph": 6.26
        },
        {
          "timestamp": "2026-02-21T07:00:00Z",
          "soil_moisture": 29.35,
          "ec": 1.12,
          "soil_temperature": 21.67,
          "ph": 6.32
        },
        {
          "timestamp": "2026-02-21T08:00:00Z",
          "soil_moisture": 30.13,
          "ec": 1.15,
          "soil_temperature": 22.29,
          "ph": 6.27
        },
        {
          "timestamp": "2026-02-21T09:00:00Z",
          "soil_moisture": 29.19,
          "ec": 1.17,
          "soil_temperature": 23.11,
          "ph": 6.33
        },
        {
          "timestamp": "2026-02-21T10:00:00Z",
          "soil_moisture": 28.66,
          "ec": 1.13,
          "soil_temperature": 23.35,
          "ph": 6.28
        },
        {
          "timestamp": "2026-02-21T11:00:00Z",
          "soil_moisture": 29.59,
          "ec": 1.15,
          "soil_temperature": 23.63,
          "ph": 6.27
        },
        {
          "timestamp": "2026-02-21T12:00:00Z",
          "soil_moisture": 29.28,
          "ec": 1.18,
          "soil_temperature": 24.34,
          "ph": 6.34
        },
        {
          "timestamp": "2026-02-21T13:00:00Z",
          "soil_moisture": 29.78,
          "ec": 1.16,
          "soil_temperature": 24.01,
          "ph": 6.3
        },
        {
          "timestamp": "2026-02-21T14:00:00Z",
          "soil_moisture": 30.94,
          "ec": 1.17,
          "soil_temperature": 25.31,
          "ph": 6.33
        }
      ]
    },
    {
      "sensor_id": "s_06",
      "status": "active",
      "battery_level": 67,
      "readings": [
        {
          "timestamp": "2026-02-20T15:00:00Z",
          "soil_moisture": 26.25,
          "ec": 1.09,
          "soil_temperature": 15.92,
          "ph": 6.31
        },
        {
          "timestamp": "2026-02-20T16:00:00Z",
          "soil_moisture": 28.03,
          "ec": 1.12,
          "soil_temperature": 16.38,
          "ph": 6.27
        },
        {
          "timestamp": "2026-02-20T17:00:00Z",
          "soil_moisture": 27.39,
          "ec": 1.09,
          "soil_temperature": 16.06,
          "ph": 6.33
        },
        {
          "timestamp": "2026-02-20T18:00:00Z",
          "soil_moisture": 26.96,
          "ec": 1.13,
          "soil_temperature": 17.2,
          "ph": 6.29
        },
        {
          "timestamp": "2026-02-20T19:00:00Z",
          "soil_moisture": 28.14,
          "ec": 1.12,
          "soil_temperature": 17.14,
          "ph": 6.27
        },
        {
          "timestamp": "2026-02-20T20:00:00Z",
          "soil_moisture": 28.34,
          "ec": 1.12,
          "soil_temperature": 17.58,
          "ph": 6.29
        },
        {
          "timestamp": "2026-02-20T21:00:00Z",
          "soil_moisture": 28.69,
          "ec": 1.13,
          "soil_temperature": 18.3,
          "ph": 6.29
        },
        {
          "timestamp": "2026-02-20T22:00:00Z",
          "soil_moisture": 28.09,
          "ec": 1.15,
          "soil_temperature": 18.57,
          "ph": 6.28
        },
        {
          "timestamp": "2026-02-20T23:00:00Z",
          "soil_moisture": 27.94,
          "ec": 1.15,
          "soil_temperature": 19.33,
          "ph": 6.28
        },
        {
          "timestamp": "2026-02-21T00:00:00Z",
          "soil_moisture": 29.27,
          "ec": 1.12,
          "soil_temperature": 19.67,
          "ph": 6.32
        },
        {
          "timestamp": "2026-02-21T01:00:00Z",
          "soil_moisture": 29.04,
          "ec": 1.14,
          "soil_temperature": 19.41,
          "ph": 6.29
        },
        {
          "timestamp": "2026-02-21T02:00:00Z",
          "soil_moisture": 28.91,
          "ec": 1.12,
          "soil_temperature": 20.01,
          "ph": 6.26
        },
        {
          "timestamp": "2026-02-21T03:00:00Z",
          "soil_moisture": 28.09,
          "ec": 1.16,
          "soil_temperature": 20.43,
          "ph": 6.32
        },
        {
          "timestamp": "2026-02-21T04:00:00Z",
          "soil_moisture": 28.96,
          "ec": 1.12,
          "soil_temperature": 20.64,
          "ph": 6.25
        },
        {
          "timestamp": "2026-02-21T05:00:00Z",
          "soil_moisture": 28.18,
          "ec": 1.14,
          "soil_temperature": 21.36,
          "ph": 6.29
        },
        {
          "timestamp": "2026-02-21T06:00:00Z",
          "soil_moisture": 30.02,
          "ec": 1.16,
          "soil_temperature": 21.97,
          "ph": 6.33
        },
        {
          "timestamp": "2026-02-21T07:00:00Z",
          "soil_moisture": 28.97,
          "ec": 1.16,
          "soil_temperature": 21.92,
          "ph": 6.29
        },
        {
          "timestamp": "2026-02-21T08:00:00Z",
          "soil_moisture": 30.35,
          "ec": 1.13,
          "soil_temperature": 22.84,
          "ph": 6.33
        },
        {
          "timestamp": "2026-02-21T09:00:00Z",
          "soil_moisture": 29.28,
          "ec": 1.17,
          "soil_temperature": 22.58,
          "ph": 6.32
        },
        {
          "timestamp": "2026-02-21T10:00:00Z",
          "soil_moisture": 28.98,
          "ec": 1.13,
          "soil_temperature": 23.47,
          "ph": 6.3
        },
        {
          "timestamp": "2026-02-21T11:00:00Z",
          "soil_moisture": 29.65,
          "ec": 1.17,
          "soil_temperature": 23.54,
          "ph": 6.28
        },
        {
          "timestamp": "2026-02-21T12:00:00Z",
          "soil_moisture": 28.85,
          "ec": 1.17,
          "soil_temperature": 23.69,
          "ph": 6.26
        },
        {
          "timestamp": "2026-02-21T13:00:00Z",
          "soil_moisture": 29.68,
          "ec": 1.14,
          "soil_temperature": 24.8,
          "ph": 6.34
        },
        {
          "timestamp": "2026-02-21T14:00:00Z",
          "soil_moisture": 30.57,
          "ec": 1.17,
          "soil_temperature": 25.1,
          "ph": 6.28
        }
      ]
    },
    {
      "sensor_id": "s_07",
      "status": "active",
      "battery_level": 63,
      "readings": [
        {
          "timestamp": "2026-02-20T15:00:00Z",
          "soil_moisture": 27.6,
          "ec": 1.12,
          "soil_temperature": 15.75,
          "ph": 6.27
        },
        {
          "timestamp": "2026-02-20T16:00:00Z",
          "soil_moisture": 27.27,
          "ec": 1.08,
          "soil_temperature": 15.92,
          "ph": 6.33
        },
        {
          "timestamp": "2026-02-20T17:00:00Z",
          "soil_moisture": 27.34,
          "ec": 1.09,
          "soil_temperature": 16.47,
          "ph": 6.34
        },
        {
          "timestamp": "2026-02-20T18:00:00Z",
          "soil_moisture": 26.87,
          "ec": 1.1,
          "soil_temperature": 16.42,
          "ph": 6.32
        },
        {
          "timestamp": "2026-02-20T19:00:00Z",
          "soil_moisture": 28.56,
          "ec": 1.11,
          "soil_temperature": 16.92,
          "ph": 6.33
        },
        {
          "timestamp": "2026-02-20T20:00:00Z",
          "soil_moisture": 27.81,
          "ec": 1.11,
          "soil_temperature": 17.3,
          "ph": 6.3
        },
        {
          "timestamp": "2026-02-20T21:00:00Z",
          "soil_moisture": 26.99,
          "ec": 1.11,
          "soil_temperature": 18.49,
          "ph": 6.26
        },
        {
          "timestamp": "2026-02-20T22:00:00Z",
          "soil_moisture": 28.43,
          "ec": 1.11,
          "soil_temperature": 18.37,
          "ph": 6.3
        },
        {
          "timestamp": "2026-02-20T23:00:00Z",
          "soil_moisture": 27.54,
          "ec": 1.1,
          "soil_temperature": 19.37,
          "ph": 6.28
        },
        {
          "timestamp": "2026-02-21T00:00:00Z",
          "soil_moisture": 29.17,
          "ec": 1.13,
          "soil_temperature": 19.6,
          "ph": 6.25
        },
        {
          "timestamp": "2026-02-21T01:00:00Z",
          "soil_moisture": 28.5,
          "ec": 1.12,
          "soil_temperature": 19.95,
          "ph": 6.32
        },
        {
          "timestamp": "2026-02-21T02:00:00Z",
          "soil_moisture": 28.7,
          "ec": 1.1,
          "soil_temperature": 20.44,
          "ph": 6.28
        },
        {
          "timestamp": "2026-02-21T03:00:00Z",
          "soil_moisture": 28.4,
          "ec": 1.11,
          "soil_temperature": 21.0,
          "ph": 6.34
        },
        {
          "timestamp": "2026-02-21T04:00:00Z",
          "soil_moisture": 28.41,
          "ec": 1.14,
          "soil_temperature": 20.92,
          "ph": 6.26
        },
        {
          "timestamp": "2026-02-21T05:00:00Z",
          "soil_moisture": 30.01,
          "ec": 1.17,
          "soil_temperature": 21.49,
          "ph": 6.34
        },
        {
          "timestamp": "2026-02-21T06:00:00Z",
          "soil_moisture": 28.67,
          "ec": 1.16,
          "soil_temperature": 21.44,
          "ph": 6.25
        },
        {
          "timestamp": "2026-02-21T07:00:00Z",
          "soil_moisture": 30.09,
          "ec": 1.13,
          "soil_temperature": 22.03,
          "ph": 6.26
        },
        {
          "timestamp": "2026-02-21T08:00:00Z",
          "soil_moisture": 29.79,
          "ec": 1.12,
          "soil_temperature": 22.3,
          "ph": 6.31
        },
        {
          "timestamp": "2026-02-21T09:00:00Z",
          "soil_moisture": 29.51,
          "ec": 1.17,
          "soil_temperature": 22.85,
          "ph": 6.28
        },
        {
          "timestamp": "2026-02-21T10:00:00Z",
          "soil_moisture": 29.21,
          "ec": 1.17,
          "soil_temperature": 23.09,
          "ph": 6.29
        },
        {
          "timestamp": "2026-02-21T11:00:00Z",
          "soil_moisture": 30.56,
          "ec": 1.17,
          "soil_temperature": 24.18,
          "ph": 6.31
        },
        {
          "timestamp": "2026-02-21T12:00:00Z",
          "soil_moisture": 29.38,
          "ec": 1.18,
          "soil_temperature": 24.01,
          "ph": 6.33
        },
        {
          "timestamp": "2026-02-21T13:00:00Z",
          "soil_moisture": 29.59,
          "ec": 1.15,
          "soil_temperature": 24.53,
          "ph": 6.35
        },
        {
          "timestamp": "2026-02-21T14:00:00Z",
          "soil_moisture": 30.74,
          "ec": 1.14,
          "soil_temperature": 24.47,
          "ph": 6.33
        }
      ]
    },
    {
      "sensor_id": "s_08",
      "status": "active",
      "battery_level": 53,
      "readings": [
        {
          "timestamp": "2026-02-20T15:00:00Z",
          "soil_moisture": 27.63,
          "ec": 1.11,
          "soil_temperature": 15.59,
          "ph": 6.26
        },
        {
          "timestamp": "2026-02-20T16:00:00Z",
          "soil_moisture": 27.58,
          "ec": 1.12,
          "soil_temperature": 15.9,
          "ph": 6.28
        },
        {
          "timestamp": "2026-02-20T17:00:00Z",
          "soil_moisture": 26.91,
          "ec": 1.1,
          "soil_temperature": 16.92,
          "ph": 6.25
        },
        {
          "timestamp": "2026-02-20T18:00:00Z",
          "soil_moisture": 28.4,
          "ec": 1.11,
          "soil_temperature": 16.51,
          "ph": 6.3
        },
        {
          "timestamp": "2026-02-20T19:00:00Z",
          "soil_moisture": 28.57,
          "ec": 1.11,
          "soil_temperature": 17.76,
          "ph": 6.26
        },
        {
          "timestamp": "2026-02-20T20:00:00Z",
          "soil_moisture": 26.97,
          "ec": 1.13,
          "soil_temperature": 17.3,
          "ph": 6.3
        },
        {
          "timestamp": "2026-02-20T21:00:00Z",
          "soil_moisture": 28.88,
          "ec": 1.12,
          "soil_temperature": 18.32,
          "ph": 6.25
        },
        {
          "timestamp": "2026-02-20T22:00:00Z",
          "soil_moisture": 28.12,
          "ec": 1.14,
          "soil_temperature": 18.96,
          "ph": 6.32
        },
        {
          "timestamp": "2026-02-20T23:00:00Z",
          "soil_moisture": 27.7,
          "ec": 1.12,
          "soil_temperature": 18.85,
          "ph": 6.31
        },
        {
          "timestamp": "2026-02-21T00:00:00Z",
          "soil_moisture": 28.27,
          "ec": 1.1,
          "soil_temperature": 19.1,
          "ph": 6.33
        },
        {
          "timestamp": "2026-02-21T01:00:00Z",
          "soil_moisture": 28.24,
          "ec": 1.15,
          "soil_temperature": 20.1,
          "ph": 6.29
        },
        {
          "timestamp": "2026-02-21T02:00:00Z",
          "soil_moisture": 28.88,
          "ec": 1.14,
          "soil_temperature": 20.37,
          "ph": 6.3
        },
        {
          "timestamp": "2026-02-21T03:00:00Z",
          "soil_moisture": 28.69,
          "ec": 1.12,
          "soil_temperature": 20.39,
          "ph": 6.3
        },
        {
          "timestamp": "2026-02-21T04:00:00Z",
          "soil_moisture": 29.14,
          "ec": 1.12,
          "soil_temperature": 20.74,
          "ph": 6.29
        },
        {
          "timestamp": "2026-02-21T05:00:00Z",
          "soil_moisture": 29.33,
          "ec": 1.17,
          "soil_temperature": 21.06,
          "ph": 6.3
        },
        {
          "timestamp": "2026-02-21T06:00:00Z",
          "soil_moisture": 28.56,
          "ec": 1.14,
          "soil_temperature": 21.45,
          "ph": 6.3
        },
        {
          "timestamp": "2026-02-21T07:00:00Z",
          "soil_moisture": 28.53,
          "ec": 1.17,
          "soil_temperature": 22.02,
          "ph": 6.34
        },
        {
          "timestamp": "2026-02-21T08:00:00Z",
          "soil_moisture": 29.24,
          "ec": 1.13,
          "soil_temperature": 22.06,
          "ph": 6.28
        },
        {
          "timestamp": "2026-02-21T09:00:00Z",
          "soil_moisture": 28.57,
          "ec": 1.15,
          "soil_temperature": 22.73,
          "ph": 6.32
        },
        {
          "timestamp": "2026-02-21T10:00:00Z",
          "soil_moisture": 28.72,
          "ec": 1.12,
          "soil_temperature": 23.15,
          "ph": 6.34
        },
        {
          "timestamp": "2026-02-21T11:00:00Z",
          "soil_moisture": 30.44,
          "ec": 1.16,
          "soil_temperature": 24.09,
          "ph": 6.3
        },
        {
          "timestamp": "2026-02-21T12:00:00Z",
          "soil_moisture": 29.93,
          "ec": 1.13,
          "soil_temperature": 24.33,
          "ph": 6.35
        },
        {
          "timestamp": "2026-02-21T13:00:00Z",
          "soil_moisture": 30.23,
          "ec": 1.14,
          "soil_temperature": 24.35,
          "ph": 6.34
        },
        {
          "timestamp": "2026-02-21T14:00:00Z",
          "soil_moisture": 30.45,
          "ec": 1.17,
          "soil_temperature": 24.76,
          "ph": 6.3
        }
      ]
    },
    {
      "sensor_id": "s_09",
      "status": "active",
      "battery_level": 57,
      "readings": [
        {
          "timestamp": "2026-02-20T15:00:00Z",
          "soil_moisture": 27.76,
          "ec": 1.09,
          "soil_temperature": 16.08,
          "ph": 6.3
        },
        {
          "timestamp": "2026-02-20T16:00:00Z",
          "soil_moisture": 28.05,
          "ec": 1.12,
          "soil_temperature": 15.97,
          "ph": 6.33
        },
        {
          "timestamp": "2026-02-20T17:00:00Z",
          "soil_moisture": 27.48,
          "ec": 1.08,
          "soil_temperature": 16.61,
          "ph": 6.34
        },
        {
          "timestamp": "2026-02-20T18:00:00Z",
          "soil_moisture": 27.67,
          "ec": 1.12,
          "soil_temperature": 17.29,
          "ph": 6.33
        },
        {
          "timestamp": "2026-02-20T19:00:00Z",
          "soil_moisture": 27.78,
          "ec": 1.13,
          "soil_temperature": 17.26,
          "ph": 6.33
        },
        {
          "timestamp": "2026-02-20T20:00:00Z",
          "soil_moisture": 28.17,
          "ec": 1.09,
          "soil_temperature": 17.47,
          "ph": 6.35
        },
        {
          "timestamp": "2026-02-20T21:00:00Z",
          "soil_moisture": 26.93,
          "ec": 1.11,
          "soil_temperature": 17.82,
          "ph": 6.27
        },
        {
          "timestamp": "2026-02-20T22:00:00Z",
          "soil_moisture": 27.41,
          "ec": 1.11,
          "soil_temperature": 18.14,
          "ph": 6.27
        },
        {
          "timestamp": "2026-02-20T23:00:00Z",
          "soil_moisture": 28.23,
          "ec": 1.1,
          "soil_temperature": 18.68,
          "ph": 6.35
        },
        {
          "timestamp": "2026-02-21T00:00:00Z",
          "soil_moisture": 28.07,
          "ec": 1.13,
          "soil_temperature": 19.4,
          "ph": 6.33
        },
        {
          "timestamp": "2026-02-21T01:00:00Z",
          "soil_moisture": 29.21,
          "ec": 1.15,
          "soil_temperature": 19.74,
          "ph": 6.35
        },
        {
          "timestamp": "2026-02-21T02:00:00Z",
          "soil_moisture": 28.32,
          "ec": 1.11,
          "soil_temperature": 19.8,
          "ph": 6.28
        },
        {
          "timestamp": "2026-02-21T03:00:00Z",
          "soil_moisture": 28.85,
          "ec": 1.16,
          "soil_temperature": 20.91,
          "ph": 6.29
        },
        {
          "timestamp": "2026-02-21T04:00:00Z",
          "soil_moisture": 29.62,
          "ec": 1.11,
          "soil_temperature": 21.19,
          "ph": 6.28
        },
        {
          "timestamp": "2026-02-21T05:00:00Z",
          "soil_moisture": 28.56,
          "ec": 1.15,
          "soil_temperature": 21.1,
          "ph": 6.33
        },
        {
          "timestamp": "2026-02-21T06:00:00Z",
          "soil_moisture": 28.82,
          "ec": 1.12,
          "soil_temperature": 21.27,
          "ph": 6.35
        },
        {
          "timestamp": "2026-02-21T07:00:00Z",
          "soil_moisture": 29.6,
          "ec": 1.15,
          "soil_temperature": 22.06,
          "ph": 6.25
        },
        {
          "timestamp": "2026-02-21T08:00:00Z",
          "soil_moisture": 28.46,
          "ec": 1.12,
          "soil_temperature": 22.08,
          "ph": 6.33
        },
        {
          "timestamp": "2026-02-21T09:00:00Z",
          "soil_moisture": 28.57,
          "ec": 1.14,
          "soil_temperature": 22.92,
          "ph": 6.27
        },
        {
          "timestamp": "2026-02-21T10:00:00Z",
          "soil_moisture": 29.28,
          "ec": 1.13,
          "soil_temperature": 23.52,
          "ph": 6.25
        },
        {
          "timestamp": "2026-02-21T11:00:00Z",
          "soil_moisture": 29.23,
          "ec": 1.14,
          "soil_temperature": 23.42,
          "ph": 6.31
        },
        {
          "timestamp": "2026-02-21T12:00:00Z",
          "soil_moisture": 30.03,
          "ec": 1.17,
          "soil_temperature": 23.78,
          "ph": 6.33
        },
        {
          "timestamp": "2026-02-21T13:00:00Z",
          "soil_moisture": 30.51,
          "ec": 1.18,
          "soil_temperature": 24.58,
          "ph": 6.31
        },
        {
          "timestamp": "2026-02-21T14:00:00Z",
          "soil_moisture": 29.91,
          "ec": 1.16,
          "soil_temperature": 24.41,
          "ph": 6.28
        }
      ]
    },
    {
      "sensor_id": "s_10",
      "status": "active",
      "battery_level": 66,
      "readings": [
        {
          "timestamp": "2026-02-20T15:00:00Z",
          "soil_moisture": 26.73,
          "ec": 1.08,
          "soil_temperature": 16.16,
          "ph": 6.25
        },
        {
          "timestamp": "2026-02-20T16:00:00Z",
          "soil_moisture": 27.8,
          "ec": 1.09,
          "soil_temperature": 16.07,
          "ph": 6.28
        },
        {
          "timestamp": "2026-02-20T17:00:00Z",
          "soil_moisture": 26.98,
          "ec": 1.1,
          "soil_temperature": 16.05,
          "ph": 6.32
        },
        {
          "timestamp": "2026-02-20T18:00:00Z",
          "soil_moisture": 27.44,
          "ec": 1.14,
          "soil_temperature": 16.61,
          "ph": 6.33
        },
        {
          "timestamp": "2026-02-20T19:00:00Z",
          "soil_moisture": 27.73,
          "ec": 1.14,
          "soil_temperature": 17.42,
          "ph": 6.34
        },
        {
          "timestamp": "2026-02-20T20:00:00Z",
          "soil_moisture": 27.39,
          "ec": 1.13,
          "soil_temperature": 17.56,
          "ph": 6.34
        },
        {
          "timestamp": "2026-02-20T21:00:00Z",
          "soil_moisture": 28.03,
          "ec": 1.14,
          "soil_temperature": 17.98,
          "ph": 6.28
        },
        {
          "timestamp": "2026-02-20T22:00:00Z",
          "soil_moisture": 27.48,
          "ec": 1.11,
          "soil_temperature": 18.24,
          "ph": 6.31
        },
        {
          "timestamp": "2026-02-20T23:00:00Z",
          "soil_moisture": 28.97,
          "ec": 1.1,
          "soil_temperature": 19.01,
          "ph": 6.26
        },
        {
          "timestamp": "2026-02-21T00:00:00Z",
          "soil_moisture": 28.49,
          "ec": 1.14,
          "soil_temperature": 19.2,
          "ph": 6.31
        },
        {
          "timestamp": "2026-02-21T01:00:00Z",
          "soil_moisture": 27.72,
          "ec": 1.13,
          "soil_temperature": 19.66,
          "ph": 6.29
        },
        {
          "timestamp": "2026-02-21T02:00:00Z",
          "soil_moisture": 28.16,
          "ec": 1.15,
          "soil_temperature": 19.72,
          "ph": 6.31
        },
        {
          "timestamp": "2026-02-21T03:00:00Z",
          "soil_moisture": 28.84,
          "ec": 1.11,
          "soil_temperature": 20.71,
          "ph": 6.34
        },
        {
          "timestamp": "2026-02-21T04:00:00Z",
          "soil_moisture": 29.03,
          "ec": 1.14,
          "soil_temperature": 20.96,
          "ph": 6.29
        },
        {
          "timestamp": "2026-02-21T05:00:00Z",
          "soil_moisture": 28.88,
          "ec": 1.14,
          "soil_temperature": 20.92,
          "ph": 6.34
        },
        {
          "timestamp": "2026-02-21T06:00:00Z",
          "soil_moisture": 28.81,
          "ec": 1.15,
          "soil_temperature": 21.43,
          "ph": 6.34
        },
        {
          "timestamp": "2026-02-21T07:00:00Z",
          "soil_moisture": 29.79,
          "ec": 1.16,
          "soil_temperature": 22.37,
          "ph": 6.34
        },
        {
          "timestamp": "2026-02-21T08:00:00Z",
          "soil_moisture": 29.95,
          "ec": 1.18,
          "soil_temperature": 22.97,
          "ph": 6.25
        },
        {
          "timestamp": "2026-02-21T09:00:00Z",
          "soil_moisture": 30.14,
          "ec": 1.16,
          "soil_temperature": 22.75,
          "ph": 6.32
        },
        {
          "timestamp": "2026-02-21T10:00:00Z",
          "soil_moisture": 30.02,
          "ec": 1.15,
          "soil_temperature": 23.22,
          "ph": 6.33
        },
        {
          "timestamp": "2026-02-21T11:00:00Z",
          "soil_moisture": 30.37,
          "ec": 1.13,
          "soil_temperature": 23.45,
          "ph": 6.27
        },
        {
          "timestamp": "2026-02-21T12:00:00Z",
          "soil_moisture": 28.91,
          "ec": 1.17,
          "soil_temperature": 23.62,
          "ph": 6.33
        },
        {
          "timestamp": "2026-02-21T13:00:00Z",
          "soil_moisture": 30.18,
          "ec": 1.17,
          "soil_temperature": 24.31,
          "ph": 6.26
        },
        {
          "timestamp": "2026-02-21T14:00:00Z",
          "soil_moisture": 30.92,
          "ec": 1.17,
          "soil_temperature": 24.57,
          "ph": 6.35
        }
      ]
    }
  ]
}