{
  "field_id": "zone_5",
  "sensors": [
    {
      "sensor_id": "s_41",
      "status": "active",
      "battery_level": 64,
      "readings": [
        {
          "timestamp": "2026-02-20T15:00:00Z",
          "soil_moisture": 35.55,
          "ec": 1.47,
          "soil_temperature": 17.25,
          "ph": 6.69
        },
        {
          "timestamp": "2026-02-20T16:00:00Z",
          "soil_moisture": 34.96,
          "ec": 1.51,
          "soil_temperature": 18.02,
          "ph": 6.67
        },
        {
          "timestamp": "2026-02-20T17:00:00Z",
          "soil_moisture": 35.66,
          "ec": 1.51,
          "soil_temperature": 18.89,
          "ph": 6.68
        },
        {
          "timestamp": "2026-02-20T18:00:00Z",
          "soil_moisture": 36.4,
          "ec": 1.53,
          "soil_temperature": 19.16,
          "ph": 6.74
        },
        {
          "timestamp": "2026-02-20T19:00:00Z",
          "soil_moisture": 34.65,
          "ec": 1.51,
          "soil_temperature": 19.1,
          "ph": 6.65
        },
        {
          "timestamp": "2026-02-20T20:00:00Z",
          "soil_moisture": 36.56,
          "ec": 1.5,
          "soil_temperature": 19.37,
          "ph": 6.73
        },
        {
          "timestamp": "2026-02-20T21:00:00Z",
          "soil_moisture": 35.86,
          "ec": 1.54,
          "soil_temperature": 19.95,
          "ph": 6.68
        },
        {
          "timestamp": "2026-02-20T22:00:00Z",
          "soil_moisture": 36.7,
          "ec": 1.53,
          "soil_temperature": 20.18,
          "ph": 6.67
        },
        {
          "timestamp": "2026-02-20T23:00:00Z",
          "soil_moisture": 36.99,
          "ec": 1.51,
          "soil_temperature": 20.67,
          "ph": 6.73
        },
        {
          "timestamp": "2026-02-21T00:00:00Z",
          "soil_moisture": 36.59,
          "ec": 1.51,
          "soil_temperature": 21.45,
          "ph": 6.75
        },
        {
          "timestamp": "2026-02-21T01:00:00Z",
          "soil_moisture": 36.24,
          "ec": 1.54,
          "soil_temperature": 21.9,
          "ph": 6.66
        },
        {
          "timestamp": "2026-02-21T02:00:00Z",
          "soil_moisture": 35.74,
          "ec": 1.55,
          "soil_temperature": 21.92,
          "ph": 6.7
        },
        {
          "timestamp": "2026-02-21T03:00:00Z",
          "soil_moisture": 37.26,
          "ec": 1.52,
          "soil_temperature": 22.78,
          "ph": 6.69
        },
        {
          "timestamp": "2026-02-21T04:00:00Z",
          "soil_moisture": 36.55,
          "ec": 1.56,
          "soil_temperature": 22.46,
          "ph": 6.7
        },
        {
          "timestamp": "2026-02-21T05:00:00Z",
          "soil_moisture": 37.33,
          "ec": 1.57,
          "soil_temperature": 23.11,
          "ph": 6.66
        },
        {
          "timestamp": "2026-02-21T06:00:00Z",
          "soil_moisture": 37.49,
          "ec": 1.54,
          "soil_temperature": 23.97,
          "ph": 6.66
        },
        {
          "timestamp": "2026-02-21T07:00:00Z",
          "soil_moisture": 37.96,
          "ec": 1.53,
          "soil_temperature": 24.29,
          "ph": 6.67
        },
        {
          "timestamp": "2026-02-21T08:00:00Z",
          "soil_moisture": 37.06,
          "ec": 1.53,
          "soil_temperature": 24.82,
          "ph": 6.75
        },
        {
          "timestamp": "2026-02-21T09:00:00Z",
          "soil_moisture": 36.59,
          "ec": 1.56,
          "soil_temperature": 24.79,
          "ph": 6.66
        },
        {
          "timestamp": "2026-02-21T10:00:00Z",
          "soil_moisture": 37.96,
          "ec": 1.55,
          "soil_temperature": 25.46,
          "ph": 6.73
        },
        {
          "timestamp": "2026-02-21T11:00:00Z",
          "soil_moisture": 38.18,
          "ec": 1.58,
          "soil_temperature": 25.31,
          "ph": 6.69
        },
        {
          "timestamp": "2026-02-21T12:00:00Z",
          "soil_moisture": 37.46,
          "ec": 1.53,
          "soil_temperature": 25.82,
          "ph": 6.74
        },
        {
          "timestamp": "2026-02-21T13:00:00Z",
          "soil_moisture": 38.48,
          "ec": 1.55,
          "soil_temperature": 26.31,
          "ph": 6.73
        },
        {
          "timestamp": "2026-02-21T14:00:00Z",
          "soil_moisture": 36.96,
          "ec": 1.58,
          "soil_temperature": 26.82,
          "ph": 6.69
        }
      ]
    },
    {
      "sensor_id": "s_42",
      "status": "active",
      "battery_level": 58,
      "readings": [
        {
          "timestamp": "2026-02-20T15:00:00Z",
          "soil_moisture": 19.09,
          "ec": 1.5,
          "soil_temperature": 17.68,
          "ph": 6.71
        },
        {
          "timestamp": "2026-02-20T16:00:00Z",
          "soil_moisture": 20.41,
          "ec": 1.53,
          "soil_temperature": 17.77,
          "ph": 6.71
        },
        {
          "timestamp": "2026-02-20T17:00:00Z",
          "soil_moisture": 20.39,
          "ec": 1.53,
          "soil_temperature": 18.23,
          "ph": 6.69
        },
        {
          "timestamp": "2026-02-20T18:00:00Z",
          "soil_moisture": 20.08,
          "ec": 1.48,
          "soil_temperature": 18.59,
          "ph": 6.75
        },
        {
          "timestamp": "2026-02-20T19:00:00Z",
          "soil_moisture": 21.18,
          "ec": 1.51,
          "soil_temperature": 19.72,
          "ph": 6.66
        },
        {
          "timestamp": "2026-02-20T20:00:00Z",
          "soil_moisture": 21.5,
          "ec": 1.5,
          "soil_temperature": 20.04,
          "ph": 6.74
        },
        {
          "timestamp": "2026-02-20T21:00:00Z",
          "soil_moisture": 21.8,
          "ec": 1.51,
          "soil_temperature": 20.29,
          "ph": 6.73
        },
        {
          "timestamp": "2026-02-20T22:00:00Z",
          "soil_moisture": 21.97,
          "ec": 1.54,
          "soil_temperature": 20.34,
          "ph": 6.66
        },
        {
          "timestamp": "2026-02-20T23:00:00Z",
          "soil_moisture": 22.13,
          "ec": 1.52,
          "soil_temperature": 20.74,
          "ph": 6.69
        },
        {
          "timestamp": "2026-02-21T00:00:00Z",
          "soil_moisture": 21.57,
          "ec": 1.56,
          "soil_temperature": 21.7,
          "ph": 6.7
        },
        {
          "timestamp": "2026-02-21T01:00:00Z",
          "soil_moisture": 21.8,
          "ec": 1.55,
          "soil_temperature": 21.5,
          "ph": 6.72
        },
        {
          "timestamp": "2026-02-21T02:00:00Z",
          "soil_moisture": 21.56,
          "ec": 1.55,
          "soil_temperature": 21.61,
          "ph": 6.69
        },
        {
          "timestamp": "2026-02-21T03:00:00Z",
          "soil_moisture": 22.08,
          "ec": 1.52,
          "soil_temperature": 22.35,
          "ph": 6.73
        },
        {
          "timestamp": "2026-02-21T04:00:00Z",
          "soil_moisture": 21.11,
          "ec": 1.52,
          "soil_temperature": 23.33,
          "ph": 6.67
        },
        {
          "timestamp": "2026-02-21T05:00:00Z",
          "soil_moisture": 22.12,
          "ec": 1.56,
          "soil_temperature": 23.1,
          "ph": 6.74
        },
        {
          "timestamp": "2026-02-21T06:00:00Z",
          "soil_moisture": 22.14,
          "ec": 1.52,
          "soil_temperature": 23.8,
          "ph": 6.67
        },
        {
          "timestamp": "2026-02-21T07:00:00Z",
          "soil_moisture": 21.34,
          "ec": 1.57,
          "soil_temperature": 24.58,
          "ph": 6.73
        },
        {
          "timestamp": "2026-02-21T08:00:00Z",
          "soil_moisture": 23.28,
          "ec": 1.57,
          "soil_temperature": 24.48,
          "ph": 6.75
        },
        {
          "timestamp": "2026-02-21T09:00:00Z",
          "soil_moisture": 23.12,
          "ec": 1.58,
          "soil_temperature": 24.83,
          "ph": 6.66
        },
        {
          "timestamp": "2026-02-21T10:00:00Z",
          "soil_moisture": 23.04,
          "ec": 1.56,
          "soil_temperature": 25.55,
          "ph": 6.68
        },
        {
          "timestamp": "2026-02-21T11:00:00Z",
          "soil_moisture": 21.83,
          "ec": 1.54,
          "soil_temperature": 25.58,
          "ph": 6.7
        },
        {
          "timestamp": "2026-02-21T12:00:00Z",
          "soil_moisture": 23.68,
          "ec": 1.53,
          "soil_temperature": 26.46,
          "ph": 6.71
        },
        {
          "timestamp": "2026-02-21T13:00:00Z",
          "soil_moisture": 23.5,
          "ec": 1.54,
          "soil_temperature": 26.87,
          "ph": 6.75
        },
        {
          "timestamp": "2026-02-21T14:00:00Z",
          "soil_moisture": 22.02,
          "ec": 1.55,
          "soil_temperature": 26.83,
          "ph": 6.71
        }
      ]
    },
    {
      "sensor_id": "s_43",
      "status": "active",
      "battery_level": 77,
      "readings": [
        {
          "timestamp": "2026-02-20T15:00:00Z",
          "soil_moisture": 35.89,
          "ec": 1.52,
          "soil_temperature": 17.76,
          "ph": 6.65
        },
        {
          "timestamp": "2026-02-20T16:00:00Z",
          "soil_moisture": 35.86,
          "ec": 1.51,
          "soil_temperature": 18.22,
          "ph": 6.72
        },
        {
          "timestamp": "2026-02-20T17:00:00Z",
          "soil_moisture": 35.65,
          "ec": 1.5,
          "soil_temperature": 18.74,
          "ph": 6.66
        },
        {
          "timestamp": "2026-02-20T18:00:00Z",
          "soil_moisture": 35.96,
          "ec": 1.53,
          "soil_temperature": 19.13,
          "ph": 6.66
        },
        {
          "timestamp": "2026-02-20T19:00:00Z",
          "soil_moisture": 34.91,
          "ec": 1.54,
          "soil_temperature": 19.27,
          "ph": 6.7
        },
        {
          "timestamp": "2026-02-20T20:00:00Z",
          "soil_moisture": 34.78,
          "ec": 1.54,
          "soil_temperature": 19.56,
          "ph": 6.66
        },
        {
          "timestamp": "2026-02-20T21:00:00Z",
          "soil_moisture": 36.73,
          "ec": 1.54,
          "soil_temperature": 20.51,
          "ph": 6.68
        },
        {
          "timestamp": "2026-02-20T22:00:00Z",
          "soil_moisture": 36.51,
          "ec": 1.5,
          "soil_temperature": 20.86,
          "ph": 6.71
        },
        {
          "timestamp": "2026-02-20T23:00:00Z",
          "soil_moisture": 36.7,
          "ec": 1.55,
          "soil_temperature": 20.54,
          "ph": 6.65
        },
        {
          "timestamp": "2026-02-21T00:00:00Z",
          "soil_moisture": 35.47,
          "ec": 1.55,
          "soil_temperature": 21.08,
          "ph": 6.7
        },
        {
          "timestamp": "2026-02-21T01:00:00Z",
          "soil_moisture": 35.78,
          "ec": 1.56,
          "soil_temperature": 21.8,
          "ph": 6.65
        },
        {
          "timestamp": "2026-02-21T02:00:00Z",
          "soil_moisture": 36.22,
          "ec": 1.54,
          "soil_temperature": 21.83,
          "ph": 6.69
        },
        {
          "timestamp": "2026-02-21T03:00:00Z",
          "soil_moisture": 35.87,
          "ec": 1.52,
          "soil_temperature": 22.76,
          "ph": 6.7
        },
        {
          "timestamp": "2026-02-21T04:00:00Z",
          "soil_moisture": 36.72,
          "ec": 1.54,
          "soil_temperature": 23.13,
          "ph": 6.73
        },
        {
          "timestamp": "2026-02-21T05:00:00Z",
          "soil_moisture": 37.79,
          "ec": 1.52,
          "soil_temperature": 23.32,
          "ph": 6.75
        },
        {
          "timestamp": "2026-02-21T06:00:00Z",
          "soil_moisture": 36.25,
          "ec": 1.53,
          "soil_temperature": 23.26,
          "ph": 6.68
        },
        {
          "timestamp": "2026-02-21T07:00:00Z",
          "soil_moisture": 37.66,
          "ec": 1.57,
          "soil_temperature": 24.35,
          "ph": 6.65
        },
        {
          "timestamp": "2026-02-21T08:00:00Z",
          "soil_moisture": 36.5,
          "ec": 1.57,
          "soil_temperature": 24.02,
          "ph": 6.65
        },
        {
          "timestamp": "2026-02-21T09:00:00Z",
          "soil_moisture": 37.44,
          "ec": 1.53,
          "soil_temperature": 25.01,
          "ph": 6.66
        },
        {
          "timestamp": "2026-02-21T10:00:00Z",
          "soil_moisture": 37.81,
          "ec": 1.55,
          "soil_temperature": 25.37,
          "ph": 6.73
        },
        {
          "timestamp": "2026-02-21T11:00:00Z",
          "soil_moisture": 37.35,
          "ec": 1.54,
          "soil_temperature": 25.3,
          "ph": 6.74
        },
        {
          "timestamp": "2026-02-21T12:00:00Z",
          "soil_moisture": 37.82,
          "ec": 1.58,
          "soil_temperature": 25.61,
          "ph": 6.72
        },
        {
          "timestamp": "2026-02-21T13:00:00Z",
          "soil_moisture": 37.88,
          "ec": 1.55,
          "soil_temperature": 26.01,
          "ph": 6.72
        },
        {
          "timestamp": "2026-02-21T14:00:00Z",
          "soil_moisture": 37.55,
          "ec": 1.59,
          "soil_temperature": 27.36,
          "ph": 6.73
        }
      ]
    },
    {
      "sensor_id": "s_44",
      "status": "active",
      "battery_level": 71,
      "readings": [
        {
          "timestamp": "2026-02-20T15:00:00Z",
          "soil_moisture": 34.5,
          "ec": 1.51,
          "soil_temperature": 18.11,
          "ph": 6.66
        },
        {
          "timestamp": "2026-02-20T16:00:00Z",
          "soil_moisture": 34.45,
          "ec": 1.51,
          "soil_temperature": 18.32,
          "ph": 6.74
        },
        {
          "timestamp": "2026-02-20T17:00:00Z",
          "soil_moisture": 34.86,
          "ec": 1.52,
          "soil_temperature": 18.15,
          "ph": 6.69
        },
        {
          "timestamp": "2026-02-20T18:00:00Z",
          "soil_moisture": 34.79,
          "ec": 1.52,
          "soil_temperature": 18.57,
          "ph": 6.66
        },
        {
          "timestamp": "2026-02-20T19:00:00Z",
          "soil_moisture": 35.66,
          "ec": 1.49,
          "soil_temperature": 19.61,
          "ph": 6.67
        },
        {
          "timestamp": "2026-02-20T20:00:00Z",
          "soil_moisture": 36.6,
          "ec": 1.49,
          "soil_temperature": 20.1,
          "ph": 6.69
        },
        {
          "timestamp": "2026-02-20T21:00:00Z",
          "soil_moisture": 35.33,
          "ec": 1.52,
          "soil_temperature": 20.52,
          "ph": 6.69
        },
        {
          "timestamp": "2026-02-20T22:00:00Z",
          "soil_moisture": 36.0,
          "ec": 1.51,
          "soil_temperature": 20.91,
          "ph": 6.7
        },
        {
          "timestamp": "2026-02-20T23:00:00Z",
          "soil_moisture": 37.11,
          "ec": 1.55,
          "soil_temperature": 20.64,
          "ph": 6.66
        },
        {
          "timestamp": "2026-02-21T00:00:00Z",
          "soil_moisture": 36.05,
          "ec": 1.54,
          "soil_temperature": 21.6,
          "ph": 6.74
        },
        {
          "timestamp": "2026-02-21T01:00:00Z",
          "soil_moisture": 36.63,
          "ec": 1.55,
          "soil_temperature": 21.34,
          "ph": 6.69
        },
        {
          "timestamp": "2026-02-21T02:00:00Z",
          "soil_moisture": 36.67,
          "ec": 1.52,
          "soil_temperature": 21.89,
          "ph": 6.72
        },
        {
          "timestamp": "2026-02-21T03:00:00Z",
          "soil_moisture": 37.12,
          "ec": 1.56,
          "soil_temperature": 22.05,
          "ph": 6.7
        },
        {
          "timestamp": "2026-02-21T04:00:00Z",
          "soil_moisture": 36.42,
          "ec": 1.55,
          "soil_temperature": 23.25,
          "ph": 6.7
        },
        {
          "timestamp": "2026-02-21T05:00:00Z",
          "soil_moisture": 36.51,
          "ec": 1.56,
          "soil_temperature": 23.36,
          "ph": 6.72
        },
        {
          "timestamp": "2026-02-21T06:00:00Z",
          "soil_moisture": 36.14,
          "ec": 1.57,
          "soil_temperature": 24.02,
          "ph": 6.71
        },
        {
          "timestamp": "2026-02-21T07:00:00Z",
          "soil_moisture": 36.54,
          "ec": 1.56,
          "soil_temperature": 24.14,
          "ph": 6.74
        },
        {
          "timestamp": "2026-02-21T08:00:00Z",
          "soil_moisture": 37.81,
          "ec": 1.56,
          "soil_temperature": 24.25,
          "ph": 6.66
        },
        {
          "timestamp": "2026-02-21T09:00:00Z",
          "soil_moisture": 37.22,
          "ec": 1.56,
          "soil_temperature": 24.62,
          "ph": 6.68
        },
        {
          "timestamp": "2026-02-21T10:00:00Z",
          "soil_moisture": 37.5,
          "ec": 1.58,
          "soil_temperature": 25.25,
          "ph": 6.74
        },
        {
          "timestamp": "2026-02-21T11:00:00Z",
          "soil_moisture": 38.01,
          "ec": 1.55,
          "soil_temperature": 25.26,
          "ph": 6.7
        },
        {
          "timestamp": "2026-02-21T12:00:00Z",
          "soil_moisture": 36.87,
          "ec": 1.54,
          "soil_temperature": 26.41,
          "ph": 6.66
        },
        {
          "timestamp": "2026-02-21T13:00:00Z",
          "soil_moisture": 37.6,
          "ec": 1.55,
          "soil_temperature": 26.11,
          "ph": 6.73
        },
        {
          "timestamp": "2026-02-21T14:00:00Z",
          "soil_moisture": 38.48,
          "ec": 1.55,
          "soil_temperature": 26.4,
          "ph": 6.75
        }
      ]
    },
    {
      "sensor_id": "s_45",
      "status": "active",
      "battery_level": 77,
      "readings": [
        {
          "timestamp": "2026-02-20T15:00:00Z",
          "soil_moisture": 35.98,
          "ec": 1.52,
          "soil_temperature": 17.59,
          "ph": 6.68
        },
        {
          "timestamp": "2026-02-20T16:00:00Z",
          "soil_moisture": 34.52,
          "ec": 1.48,
          "soil_temperature": 18.42,
          "ph": 6.74
        },
        {
          "timestamp": "2026-02-20T17:00:00Z",
          "soil_moisture": 35.43,
          "ec": 1.51,
          "soil_temperature": 18.79,
          "ph": 6.73
        },
        {
          "timestamp": "2026-02-20T18:00:00Z",
          "soil_moisture": 34.87,
          "ec": 1.54,
          "soil_temperature": 18.95,
          "ph": 6.73
        },
        {
          "timestamp": "2026-02-20T19:00:00Z",
          "soil_moisture": 36.09,
          "ec": 1.49,
          "soil_temperature": 19.35,
          "ph": 6.7
        },
        {
          "timestamp": "2026-02-20T20:00:00Z",
          "soil_moisture": 36.17,
          "ec": 1.52,
          "soil_temperature": 19.82,
          "ph": 6.69
        },
        {
          "timestamp": "2026-02-20T21:00:00Z",
          "soil_moisture": 36.61,
          "ec": 1.53,
          "soil_temperature": 19.68,
          "ph": 6.68
        },
        {
          "timestamp": "2026-02-20T22:00:00Z",
          "soil_moisture": 35.94,
          "ec": 1.52,
          "soil_temperature": 20.06,
          "ph": 6.66
        },
        {
          "timestamp": "2026-02-20T23:00:00Z",
          "soil_moisture": 36.75,
          "ec": 1.54,
          "soil_temperature": 21.29,
          "ph": 6.72
        },
        {
          "timestamp": "2026-02-21T00:00:00Z",
          "soil_moisture": 36.53,
          "ec": 1.55,
          "soil_temperature": 21.32,
          "ph": 6.68
        },
        {
          "timestamp": "2026-02-21T01:00:00Z",
          "soil_moisture": 37.36,
          "ec": 1.5,
          "soil_temperature": 22.15,
          "ph": 6.69
        },
        {
          "timestamp": "2026-02-21T02:00:00Z",
          "soil_moisture": 37.15,
          "ec": 1.51,
          "soil_temperature": 21.7,
          "ph": 6.75
        },
        {
          "timestamp": "2026-02-21T03:00:00Z",
          "soil_moisture": 36.43,
          "ec": 1.52,
          "soil_temperature": 22.7,
          "ph": 6.72
        },
        {
          "timestamp": "2026-02-21T04:00:00Z",
          "soil_moisture": 36.48,
          "ec": 1.56,
          "soil_temperature": 22.97,
          "ph": 6.75
        },
        {
          "timestamp": "2026-02-21T05:00:00Z",
          "soil_moisture": 36.28,
          "ec": 1.52,
          "soil_temperature": 23.23,
          "ph": 6.7
        },
        {
          "timestamp": "2026-02-21T06:00:00Z",
          "soil_moisture": 37.06,
          "ec": 1.56,
          "soil_temperature": 23.29,
          "ph": 6.66
        },
        {
          "timestamp": "2026-02-21T07:00:00Z",
          "soil_moisture": 37.43,
          "ec": 1.54,
          "soil_temperature": 24.23,
          "ph": 6.69
        },
        {
          "timestamp": "2026-02-21T08:00:00Z",
          "soil_moisture": 37.12,
          "ec": 1.52,
          "soil_temperature": 24.89,
          "ph": 6.66
        },
        {
          "timestamp": "2026-02-21T09:00:00Z",
          "soil_moisture": 37.41,
          "ec": 1.54,
          "soil_temperature": 24.59,
          "ph": 6.7
        },
        {
          "timestamp": "2026-02-21T10:00:00Z",
          "soil_moisture": 38.01,
          "ec": 1.52,
          "soil_temperature": 25.54,
          "ph": 6.66
        },
        {
          "timestamp": "2026-02-21T11:00:00Z",
          "soil_moisture": 38.19,
          "ec": 1.57,
          "soil_temperature": 25.52,
          "ph": 6.68
        },
        {
          "timestamp": "2026-02-21T12:00:00Z",
          "soil_moisture": 38.34,
          "ec": 1.58,
          "soil_temperature": 25.76,
          "ph": 6.75
        },
        {
          "timestamp": "2026-02-21T13:00:00Z",
          "soil_moisture": 37.28,
          "ec": 1.56,
          "soil_temperature": 26.19,
          "ph": 6.74
        },
        {
          "timestamp": "2026-02-21T14:00:00Z",
          "soil_moisture": 37.95,
          "ec": 1.56,
          "soil_temperature": 26.76,
          "ph": 6.74
        }
      ]
    },
    {
      "sensor_id": "s_46",
      "status": "active",
      "battery_level": 51,
      "readings": [
        {
          "timestamp": "2026-02-20T15:00:00Z",
          "soil_moisture": 35.67,
          "ec": 1.52,
          "soil_temperature": 17.59,
          "ph": 6.73
        },
        {
          "timestamp": "2026-02-20T16:00:00Z",
          "soil_moisture": 34.72,
          "ec": 1.48,
          "soil_temperature": 17.74,
          "ph": 6.68
        },
        {
          "timestamp": "2026-02-20T17:00:00Z",
          "soil_moisture": 35.39,
          "ec": 1.52,
          "soil_temperature": 18.57,
          "ph": 6.68
        },
        {
          "timestamp": "2026-02-20T18:00:00Z",
          "soil_moisture": 35.54,
          "ec": 1.52,
          "soil_temperature": 19.05,
          "ph": 6.66
        },
        {
          "timestamp": "2026-02-20T19:00:00Z",
          "soil_moisture": 36.1,
          "ec": 1.52,
          "soil_temperature": 19.64,
          "ph": 6.67
        },
        {
          "timestamp": "2026-02-20T20:00:00Z",
          "soil_moisture": 35.73,
          "ec": 1.51,
          "soil_temperature": 19.83,
          "ph": 6.71
        },
        {
          "timestamp": "2026-02-20T21:00:00Z",
          "soil_moisture": 36.29,
          "ec": 1.5,
          "soil_temperature": 19.92,
          "ph": 6.68
        },
        {
          "timestamp": "2026-02-20T22:00:00Z",
          "soil_moisture": 35.17,
          "ec": 1.51,
          "soil_temperature": 20.33,
          "ph": 6.7
        },
        {
          "timestamp": "2026-02-20T23:00:00Z",
          "soil_moisture": 35.29,
          "ec": 1.53,
          "soil_temperature": 20.59,
          "ph": 6.66
        },
        {
          "timestamp": "2026-02-21T00:00:00Z",
          "soil_moisture": 35.67,
          "ec": 1.54,
          "soil_temperature": 21.53,
          "ph": 6.67
        },
        {
          "timestamp": "2026-02-21T01:00:00Z",
          "soil_moisture": 35.54,
          "ec": 1.54,
          "soil_temperature": 21.42,
          "ph": 6.71
        },
        {
          "timestamp": "2026-02-21T02:00:00Z",
          "soil_moisture": 35.97,
          "ec": 1.53,
          "soil_temperature": 22.1,
          "ph": 6.74
        },
        {
          "timestamp": "2026-02-21T03:00:00Z",
          "soil_moisture": 36.15,
          "ec": 1.51,
          "soil_temperature": 22.56,
          "ph": 6.69
        },
        {
          "timestamp": "2026-02-21T04:00:00Z",
          "soil_moisture": 36.35,
          "ec": 1.52,
          "soil_temperature": 23.31,
          "ph": 6.74
        },
        {
          "timestamp": "2026-02-21T05:00:00Z",
          "soil_moisture": 36.24,
          "ec": 1.53,
          "soil_temperature": 23.27,
          "ph": 6.72
        },
        {
          "timestamp": "2026-02-21T06:00:00Z",
          "soil_moisture": 37.61,
          "ec": 1.55,
          "soil_temperature": 23.93,
          "ph": 6.66
        },
        {
          "timestamp": "2026-02-21T07:00:00Z",
          "soil_moisture": 37.11,
          "ec": 1.55,
          "soil_temperature": 24.3,
          "ph": 6.66
        },
        {
          "timestamp": "2026-02-21T08:00:00Z",
          "soil_moisture": 37.35,
          "ec": 1.54,
          "soil_temperature": 24.29,
          "ph": 6.74
        },
        {
          "timestamp": "2026-02-21T09:00:00Z",
          "soil_moisture": 36.65,
          "ec": 1.53,
          "soil_temperature": 24.65,
          "ph": 6.7
        },
        {
          "timestamp": "2026-02-21T10:00:00Z",
          "soil_moisture": 36.74,
          "ec": 1.54,
          "soil_temperature": 25.67,
          "ph": 6.72
        },
        {
          "timestamp": "2026-02-21T11:00:00Z",
          "soil_moisture": 38.51,
          "ec": 1.57,
          "soil_temperature": 25.89,
          "ph": 6.65
        },
        {
          "timestamp": "2026-02-21T12:00:00Z",
          "soil_moisture": 38.08,
          "ec": 1.56,
          "soil_temperature": 25.82,
          "ph": 6.71
        },
        {
          "timestamp": "2026-02-21T13:00:00Z",
          "soil_moisture": 37.75,
          "ec": 1.58,
          "soil_temperature": 26.04,
          "ph": 6.72
        },
        {
          "timestamp": "2026-02-21T14:00:00Z",
          "soil_moisture": 38.56,
          "ec": 1.58,
          "soil_temperature": 26.81,
          "ph": 6.69
        }
      ]
    },
    {
      "sensor_id": "s_47",
      "status": "active",
      "battery_level": 66,
      "readings": [
        {
          "timestamp": "2026-02-20T15:00:00Z",
          "soil_moisture": 34.88,
          "ec": 1.51,
          "soil_temperature": 18.02,
          "ph": 6.67
        },
        {
          "timestamp": "2026-02-20T16:00:00Z",
          "soil_moisture": 35.5,
          "ec": 1.5,
          "soil_temperature": 18.56,
          "ph": 6.73
        },
        {
          "timestamp": "2026-02-20T17:00:00Z",
          "soil_moisture": 35.75,
          "ec": 1.53,
          "soil_temperature": 18.96,
          "ph": 6.67
        },
        {
          "timestamp": "2026-02-20T18:00:00Z",
          "soil_moisture": 34.8,
          "ec": 1.49,
          "soil_temperature": 18.77,
          "ph": 6.7
        },
        {
          "timestamp": "2026-02-20T19:00:00Z",
          "soil_moisture": 36.0,
          "ec": 1.53,
          "soil_temperature": 19.39,
          "ph": 6.68
        },
        {
          "timestamp": "2026-02-20T20:00:00Z",
          "soil_moisture": 36.32,
          "ec": 1.53,
          "soil_temperature": 19.81,
          "ph": 6.7
        },
        {
          "timestamp": "2026-02-20T21:00:00Z",
          "soil_moisture": 35.7,
          "ec": 1.49,
          "soil_temperature": 20.31,
          "ph": 6.7
        },
        {
          "timestamp": "2026-02-20T22:00:00Z",
          "soil_moisture": 36.66,
          "ec": 1.5,
          "soil_temperature": 20.53,
          "ph": 6.71
        },
        {
          "timestamp": "2026-02-20T23:00:00Z",
          "soil_moisture": 37.01,
          "ec": 1.55,
          "soil_temperature": 21.19,
          "ph": 6.7
        },
        {
          "timestamp": "2026-02-21T00:00:00Z",
          "soil_moisture": 36.96,
          "ec": 1.53,
          "soil_temperature": 21.74,
          "ph": 6.74
        },
        {
          "timestamp": "2026-02-21T01:00:00Z",
          "soil_moisture": 36.44,
          "ec": 1.51,
          "soil_temperature": 21.29,
          "ph": 6.74
        },
        {
          "timestamp": "2026-02-21T02:00:00Z",
          "soil_moisture": 37.5,
          "ec": 1.53,
          "soil_temperature": 22.01,
          "ph": 6.71
        },
        {
          "timestamp": "2026-02-21T03:00:00Z",
          "soil_moisture": 36.42,
          "ec": 1.53,
          "soil_temperature": 22.66,
          "ph": 6.7
        },
        {
          "timestamp": "2026-02-21T04:00:00Z",
          "soil_moisture": 36.68,
          "ec": 1.52,
          "soil_temperature": 22.44,
          "ph": 6.68
        },
        {
          "timestamp": "2026-02-21T05:00:00Z",
          "soil_moisture": 36.21,
          "ec": 1.54,
          "soil_temperature": 23.25,
          "ph": 6.7
        },
        {
          "timestamp": "2026-02-21T06:00:00Z",
          "soil_moisture": 37.79,
          "ec": 1.54,
          "soil_temperature": 23.9,
          "ph": 6.69
        },
        {
          "timestamp": "2026-02-21T07:00:00Z",
          "soil_moisture": 36.99,
          "ec": 1.53,
          "soil_temperature": 24.51,
          "ph": 6.73
        },
        {
          "timestamp": "2026-02-21T08:00:00Z",
          "soil_moisture": 37.25,
          "ec": 1.54,
          "soil_temperature": 24.76,
          "ph": 6.72
        },
        {
          "timestamp": "2026-02-21T09:00:00Z",
          "soil_moisture": 37.42,
          "ec": 1.55,
          "soil_temperature": 24.68,
          "ph": 6.7
        },
        {
          "timestamp": "2026-02-21T10:00:00Z",
          "soil_moisture": 37.77,
          "ec": 1.53,
          "soil_temperature": 25.35,
          "ph": 6.74
        },
        {
          "timestamp": "2026-02-21T11:00:00Z",
          "soil_moisture": 37.51,
          "ec": 1.58,
          "soil_temperature": 25.76,
          "ph": 6.72
        },
        {
          "timestamp": "2026-02-21T12:00:00Z",
          "soil_moisture": 38.55,
          "ec": 1.53,
          "soil_temperature": 26.33,
          "ph": 6.66
        },
        {
          "timestamp": "2026-02-21T13:00:00Z",
          "soil_moisture": 37.81,
          "ec": 1.57,
          "soil_temperature": 26.35,
          "ph": 6.66
        },
        {
          "timestamp": "2026-02-21T14:00:00Z",
          "soil_moisture": 38.16,
          "ec": 1.58,
          "soil_temperature": 27.36,
          "ph": 6.68
        }
      ]
    },
    {
      "sensor_id": "s_48",
      "status": "active",
      "battery_level": 75,
      "readings": [
        {
          "timestamp": "2026-02-20T15:00:00Z",
          "soil_moisture": 64.22,
          "ec": 6.04,
          "soil_temperature": 2.65,
          "ph": 6.68
        },
        {
          "timestamp": "2026-02-20T16:00:00Z",
          "soil_moisture": 35.16,
          "ec": 1.48,
          "soil_temperature": 17.92,
          "ph": 6.72
        },
        {
          "timestamp": "2026-02-20T17:00:00Z",
          "soil_moisture": 34.83,
          "ec": 1.52,
          "soil_temperature": 18.37,
          "ph": 6.74
        },
        {
          "timestamp": "2026-02-20T18:00:00Z",
          "soil_moisture": 36.01,
          "ec": 1.5,
          "soil_temperature": 18.47,
          "ph": 6.66
        },
        {
          "timestamp": "2026-02-20T19:00:00Z",
          "soil_moisture": 65.51,
          "ec": 6.08,
          "soil_temperature": 3.99,
          "ph": 6.72
        },
        {
          "timestamp": "2026-02-20T20:00:00Z",
          "soil_moisture": 35.7,
          "ec": 1.51,
          "soil_temperature": 19.94,
          "ph": 6.7
        },
        {
          "timestamp": "2026-02-20T21:00:00Z",
          "soil_moisture": 35.44,
          "ec": 1.5,
          "soil_temperature": 20.43,
          "ph": 6.66
        },
        {
          "timestamp": "2026-02-20T22:00:00Z",
          "soil_moisture": 36.66,
          "ec": 1.55,
          "soil_temperature": 20.83,
          "ph": 6.71
        },
        {
          "timestamp": "2026-02-20T23:00:00Z",
          "soil_moisture": 66.12,
          "ec": 6.06,
          "soil_temperature": 5.78,
          "ph": 6.69
        },
        {
          "timestamp": "2026-02-21T00:00:00Z",
          "soil_moisture": 36.6,
          "ec": 1.55,
          "soil_temperature": 21.46,
          "ph": 6.65
        },
        {
          "timestamp": "2026-02-21T01:00:00Z",
          "soil_moisture": 36.83,
          "ec": 1.51,
          "soil_temperature": 21.68,
          "ph": 6.7
        },
        {
          "timestamp": "2026-02-21T02:00:00Z",
          "soil_moisture": 37.42,
          "ec": 1.53,
          "soil_temperature": 22.54,
          "ph": 6.69
        },
        {
          "timestamp": "2026-02-21T03:00:00Z",
          "soil_moisture": 67.09,
          "ec": 6.22,
          "soil_temperature": 7.34,
          "ph": 6.68
        },
        {
          "timestamp": "2026-02-21T04:00:00Z",
          "soil_moisture": 37.12,
          "ec": 1.53,
          "soil_temperature": 23.31,
          "ph": 6.69
        },
        {
          "timestamp": "2026-02-21T05:00:00Z",
          "soil_moisture": 37.78,
          "ec": 1.54,
          "soil_temperature": 23.78,
          "ph": 6.67
        },
        {
          "timestamp": "2026-02-21T06:00:00Z",
          "soil_moisture": 36.72,
          "ec": 1.56,
          "soil_temperature": 23.53,
          "ph": 6.65
        },
        {
          "timestamp": "2026-02-21T07:00:00Z",
          "soil_moisture": 68.09,
          "ec": 6.21,
          "soil_temperature": 9.07,
          "ph": 6.66
        },
        {
          "timestamp": "2026-02-21T08:00:00Z",
          "soil_moisture": 36.69,
          "ec": 1.56,
          "soil_temperature": 24.37,
          "ph": 6.73
        },
        {
          "timestamp": "2026-02-21T09:00:00Z",
          "soil_moisture": 38.47,
          "ec": 1.52,
          "soil_temperature": 25.27,
          "ph": 6.69
        },
        {
          "timestamp": "2026-02-21T10:00:00Z",
          "soil_moisture": 37.83,
          "ec": 1.53,
          "soil_temperature": 25.39,
          "ph": 6.73
        },
        {
          "timestamp": "2026-02-21T11:00:00Z",
          "soil_moisture": 67.46,
          "ec": 6.25,
          "soil_temperature": 10.57,
          "ph": 6.72
        },
        {
          "timestamp": "2026-02-21T12:00:00Z",
          "soil_moisture": 38.36,
          "ec": 1.57,
          "soil_temperature": 26.6,
          "ph": 6.7
        },
        {
          "timestamp": "2026-02-21T13:00:00Z",
          "soil_moisture": 38.16,
          "ec": 1.58,
          "soil_temperature": 26.4,
          "ph": 6.72
        },
        {
          "timestamp": "2026-02-21T14:00:00Z",
          "soil_moisture": 38.73,
          "ec": 1.57,
          "soil_temperature": 27.01,
          "ph": 6.73
        }
      ]
    },
    {
      "sensor_id": "s_49",
      "status": "active",
      "battery_level": 54,
      "readings": [
        {
          "timestamp": "2026-02-20T15:00:00Z",
          "soil_moisture": 35.49,
          "ec": 1.47,
          "soil_temperature": 17.86,
          "ph": 6.7
        },
        {
          "timestamp": "2026-02-20T16:00:00Z",
          "soil_moisture": 35.45,
          "ec": 1.48,
          "soil_temperature": 18.31,
          "ph": 6.69
        },
        {
          "timestamp": "2026-02-20T17:00:00Z",
          "soil_moisture": 35.45,
          "ec": 1.51,
          "soil_temperature": 18.49,
          "ph": 6.74
        },
        {
          "timestamp": "2026-02-20T18:00:00Z",
          "soil_moisture": 34.51,
          "ec": 1.49,
          "soil_temperature": 18.73,
          "ph": 6.71
        },
        {
          "timestamp": "2026-02-20T19:00:00Z",
          "soil_moisture": 34.89,
          "ec": 1.51,
          "soil_temperature": 19.62,
          "ph": 6.72
        },
        {
          "timestamp": "2026-02-20T20:00:00Z",
          "soil_moisture": 34.78,
          "ec": 1.49,
          "soil_temperature": 19.93,
          "ph": 6.74
        },
        {
          "timestamp": "2026-02-20T21:00:00Z",
          "soil_moisture": 35.29,
          "ec": 1.54,
          "soil_temperature": 19.87,
          "ph": 6.68
        },
        {
          "timestamp": "2026-02-20T22:00:00Z",
          "soil_moisture": 36.85,
          "ec": 1.5,
          "soil_temperature": 20.62,
          "ph": 6.68
        },
        {
          "timestamp": "2026-02-20T23:00:00Z",
          "soil_moisture": 35.29,
          "ec": 1.55,
          "soil_temperature": 20.77,
          "ph": 6.74
        },
        {
          "timestamp": "2026-02-21T00:00:00Z",
          "soil_moisture": 37.21,
          "ec": 1.51,
          "soil_temperature": 20.98,
          "ph": 6.69
        },
        {
          "timestamp": "2026-02-21T01:00:00Z",
          "soil_moisture": 36.8,
          "ec": 1.5,
          "soil_temperature": 21.41,
          "ph": 6.73
        },
        {
          "timestamp": "2026-02-21T02:00:00Z",
          "soil_moisture": 36.3,
          "ec": 1.55,
          "soil_temperature": 21.7,
          "ph": 6.74
        },
        {
          "timestamp": "2026-02-21T03:00:00Z",
          "soil_moisture": 36.3,
          "ec": 1.51,
          "soil_temperature": 22.58,
          "ph": 6.67
        },
        {
          "timestamp": "2026-02-21T04:00:00Z",
          "soil_moisture": 36.11,
          "ec": 1.57,
          "soil_temperature": 22.63,
          "ph": 6.68
        },
        {
          "timestamp": "2026-02-21T05:00:00Z",
          "soil_moisture": 37.54,
          "ec": 1.53,
          "soil_temperature": 23.62,
          "ph": 6.69
        },
        {
          "timestamp": "2026-02-21T06:00:00Z",
          "soil_moisture": 36.2,
          "ec": 1.55,
          "soil_temperature": 23.46,
          "ph": 6.7
        },
        {
          "timestamp": "2026-02-21T07:00:00Z",
          "soil_moisture": 37.22,
          "ec": 1.56,
          "soil_temperature": 23.86,
          "ph": 6.68
        },
        {
          "timestamp": "2026-02-21T08:00:00Z",
          "soil_moisture": 37.31,
          "ec": 1.54,
          "soil_temperature": 24.66,
          "ph": 6.66
        },
        {
          "timestamp": "2026-02-21T09:00:00Z",
          "soil_moisture": 37.31,
          "ec": 1.53,
          "soil_temperature": 24.73,
          "ph": 6.72
        },
        {
          "timestamp": "2026-02-21T10:00:00Z",
          "soil_moisture": 37.63,
          "ec": 1.57,
          "soil_temperature": 25.16,
          "ph": 6.68
        },
        {
          "timestamp": "2026-02-21T11:00:00Z",
          "soil_moisture": 37.5,
          "ec": 1.56,
          "soil_temperature": 26.08,
          "ph": 6.67
        },
        {
          "timestamp": "2026-02-21T12:00:00Z",
          "soil_moisture": 38.41,
          "ec": 1.55,
          "soil_temperature": 26.07,
          "ph": 6.67
        },
        {
          "timestamp": "2026-02-21T13:00:00Z",
          "soil_moisture": 37.95,
          "ec": 1.54,
          "soil_temperature": 26.19,
          "ph": 6.66
        },
        {
          "timestamp": "2026-02-21T14:00:00Z",
          "soil_moisture": 37.8,
          "ec": 1.54,
          "soil_temperature": 27.33,
          "ph": 6.74
        }
      ]
    },
    {
      "sensor_id": "s_50",
      "status": "active",
      "battery_level": 55,
      "readings": [
        {
          "timestamp": "2026-02-20T15:00:00Z",
          "soil_moisture": 35.71,
          "ec": 1.48,
          "soil_temperature": 17.79,
          "ph": 6.72
        },
        {
          "timestamp": "2026-02-20T16:00:00Z",
          "soil_moisture": 36.04,
          "ec": 1.51,
          "soil_temperature": 17.96,
          "ph": 6.71
        },
        {
          "timestamp": "2026-02-20T17:00:00Z",
          "soil_moisture": 35.41,
          "ec": 1.51,
          "soil_temperature": 18.9,
          "ph": 6.74
        },
        {
          "timestamp": "2026-02-20T18:00:00Z",
          "soil_moisture": 35.3,
          "ec": 1.51,
          "soil_temperature": 18.51,
          "ph": 6.66
        },
        {
          "timestamp": "2026-02-20T19:00:00Z",
          "soil_moisture": 35.79,
          "ec": 1.49,
          "soil_temperature": 18.85,
          "ph": 6.69
        },
        {
          "timestamp": "2026-02-20T20:00:00Z",
          "soil_moisture": 35.42,
          "ec": 1.52,
          "soil_temperature": 19.77,
          "ph": 6.65
        },
        {
          "timestamp": "2026-02-20T21:00:00Z",
          "soil_moisture": 35.09,
          "ec": 1.55,
          "soil_temperature": 19.87,
          "ph": 6.68
        },
        {
          "timestamp": "2026-02-20T22:00:00Z",
          "soil_moisture": 36.32,
          "ec": 1.5,
          "soil_temperature": 20.34,
          "ph": 6.74
        },
        {
          "timestamp": "2026-02-20T23:00:00Z",
          "soil_moisture": 35.5,
          "ec": 1.53,
          "soil_temperature": 21.03,
          "ph": 6.73
        },
        {
          "timestamp": "2026-02-21T00:00:00Z",
          "soil_moisture": 35.8,
          "ec": 1.55,
          "soil_temperature": 21.35,
          "ph": 6.75
        },
        {
          "timestamp": "2026-02-21T01:00:00Z",
          "soil_moisture": 37.22,
          "ec": 1.5,
          "soil_temperature": 21.83,
          "ph": 6.74
        },
        {
          "timestamp": "2026-02-21T02:00:00Z",
          "soil_moisture": 36.56,
          "ec": 1.53,
          "soil_temperature": 22.4,
          "ph": 6.69
        },
        {
          "timestamp": "2026-02-21T03:00:00Z",
          "soil_moisture": 37.56,
          "ec": 1.53,
          "soil_temperature": 22.65,
          "ph": 6.66
        },
        {
          "timestamp": "2026-02-21T04:00:00Z",
          "soil_moisture": 36.54,
          "ec": 1.52,
          "soil_temperature": 22.95,
          "ph": 6.66
        },
        {
          "timestamp": "2026-02-21T05:00:00Z",
          "soil_moisture": 37.41,
          "ec": 1.54,
          "soil_temperature": 23.02,
          "ph": 6.69
        },
        {
          "timestamp": "2026-02-21T06:00:00Z",
          "soil_moisture": 36.44,
          "ec": 1.54,
          "soil_temperature": 23.83,
          "ph": 6.67
        },
        {
          "timestamp": "2026-02-21T07:00:00Z",
          "soil_moisture": 37.66,
          "ec": 1.53,
          "soil_temperature": 23.97,
          "ph": 6.65
        },
        {
          "timestamp": "2026-02-21T08:00:00Z",
          "soil_moisture": 36.69,
          "ec": 1.54,
          "soil_temperature": 24.97,
          "ph": 6.73
        },
        {
          "timestamp": "2026-02-21T09:00:00Z",
          "soil_moisture": 38.26,
          "ec": 1.54,
          "soil_temperature": 25.22,
          "ph": 6.7
        },
        {
          "timestamp": "2026-02-21T10:00:00Z",
          "soil_moisture": 38.19,
          "ec": 1.57,
          "soil_temperature": 25.67,
          "ph": 6.7
        },
        {
          "timestamp": "2026-02-21T11:00:00Z",
          "soil_moisture": 38.48,
          "ec": 1.53,
          "soil_temperature": 25.22,
          "ph": 6.71
        },
        {
          "timestamp": "2026-02-21T12:00:00Z",
          "soil_moisture": 37.21,
          "ec": 1.56,
          "soil_temperature": 25.63,
          "ph": 6.67
        },
        {
          "timestamp": "2026-02-21T13:00:00Z",
          "soil_moisture": 38.07,
          "ec": 1.57,
          "soil_temperature": 26.64,
          "ph": 6.69
        },
        {
          "timestamp": "2026-02-21T14:00:00Z",
          "soil_moisture": 38.6,
          "ec": 1.56,
          "soil_temperature": 27.06,
          "ph": 6.66
        }
      ]
    }
  ]
}